genderize/__init__.py
genderize/__main__.py
Genderize-0.3.1.dist-info/LICENSE.txt
Genderize-0.3.1.dist-info/METADATA
Genderize-0.3.1.dist-info/WHEEL
Genderize-0.3.1.dist-info/top_level.txt
Genderize-0.3.1.dist-info/RECORD
